{
    "navbar": {
        "navbar-links": [
            {
                "name": "Home",
                "url": "#",
                "target": "_self"
            },
            {
                "name": "Links",
                "url": "#",
                "target": "_self"
            },
            {
                "name": "Docs",
                "url": "#",
                "target": "_self"
            }
        ],
        "social-links": {
            "x": {
                "url": "https://twitter.com/JPTHOR89",
                "target": "_blank"
            },
            "instagram": {
                "url": "https://www.instagram.com/jpthor/",
                "target": "_blank"
            },
            "github": {
                "url": "https://www.github.com/jpthor",
                "target": "_blank"
            },
            "tiktok": {
                "url": "https://www.tiktok.com/jpthor",
                "target": "_blank"
            },
            "youtube": {
                "url": "https://www.youtube.com/@jpthor",
                "target": "_blank"
            },
            "linkedin": {
                "url": "https://www.linkedin.com/in/jpthor/",
                "target": "_blank"
            }
        }
    },
    "footer": {
        "social-links": {
            "x": {
                "url": "https://twitter.com/JPTHOR89",
                "target": "_blank"
            },
            "instagram": {
                "url": "https://www.instagram.com/jpthor/",
                "target": "_blank"
            },
            "github": {
                "url": "https://www.github.com/jpthor",
                "target": "_blank"
            },
            "tiktok": {
                "url": "https://www.tiktok.com/jpthor",
                "target": "_blank"
            },
            "youtube": {
                "url": "https://www.youtube.com/@jpthor",
                "target": "_blank"
            },
            "linkedin": {
                "url": "https://www.linkedin.com/in/jpthor/",
                "target": "_blank"
            }
        },
        "links": {
            "projects": [
                {
                    "name": "THORChain",
                    "url": "https://thorchain.org",
                    "target": "_blank"
                },
                {
                    "name": "Vultisig",
                    "url": "https://vultisig.com",
                    "target": "_blank"
                },
                {
                    "name": "TraitForge",
                    "url": "https://traitforge.info",
                    "target": "_blank"
                },
                {
                    "name": "ACCEL Co",
                    "url": "https://www.instagram.com/accel_co",
                    "target": "_blank"
                },
                {
                    "name": "Nextgen North",
                    "url": "https://linktr.ee/nextgennorth",
                    "target": "_blank"
                }
            ],
            "entrepreneur": [
                {
                    "name": "21e8 Capital",
                    "url": "https://21e8.capital",
                    "target": "_blank"
                },
                {
                    "name": "ARRQ",
                    "url": "https://arrq.live",
                    "target": "_blank"
                }
            ],
            "resources": [
                {
                    "name": "Investments",
                    "url": "https://21e8.capital",
                    "target": "_blank"
                },
                {
                    "name": "Media & Press",
                    "url": "#",
                    "target": "_blank"
                }
            ],
            "legal": [
                {
                    "name": "Terms of Service",
                    "url": "#",
                    "target": "_blank"
                },
                {
                    "name": "Privacy Policy",
                    "url": "#",
                    "target": "_blank"
                }
            ]
        }
    },
    "home": {
        "social-tags": {
            "site-name": "JP THOR",
            "title": "JPTHOR Website",
            "description": "JP THOR, EMPOWERING ADVENTURE & INNOVATION.",
            "image": "https://jpthor.com/img/jpthor-header.png",
            "url": "https://jpthor.com",
            "twitter-card": "summary_large_image",
            "twitter-creator": "JPTHOR"
        },
        "page-title": "JPThor",
        "header": {
            "title": "Empowering <br> <span class='pl-header'>Adventure</span> <br>& Innovation.",
            "subtitle": "Unlocking the Potential of Tomorrow through the Spirit of <br> Exploration and Breakthrough Thinking."
        },
        "segment-1": {
            "title": "MEET <span class='text-green'>JP THOR</span>",
            "description": "A modern-day explorer, entrepreneur, and visionary founder, where every step is an adventure and every adventure sparks innovation. <br> <br> JP embodies a spirit of endless curiosity and a drive to push beyond the conventional boundaries of exploration and personal achievement. <br> <br> At the heart of JP's ethos is the ACCELERATE movement-a dynamic initiative that champions the fusion of high-stakes adventure, cutting-edge innovation, and profound personal growth."
        },
        "segment-2": {
            "title": "PROJECTS",
            "description": "From decentralized exchanges to secure crypto vaults, and from NFT-based games to movements accelerating growth, these projects are not just concepts but are actively transforming industries and driving forward the future of technology.",
            "cards": [
                {
                    "title": "THORChain",
                    "description": "Decentralized Exchange",
                    "url": "https://thorchain.org",
                    "target": "_blank"
                },
                {
                    "title": "Vultisig",
                    "description": "Secure Crypto Vault",
                    "url": "https://vultisig.com",
                    "target": "_blank"
                },
                {
                    "title": "TraitForge",
                    "description": "NFT Honeypot Game",
                    "url": "https://traitforge.info",
                    "target": "_blank"
                },
                {
                    "title": "ACCEL Co",
                    "description": "Accelerate Movement",
                    "url": "https://accelerateordie.org",
                    "target": "_blank"
                },
                {
                    "title": "Nextgen North",
                    "description": "Big Ideas For the North",
                    "url": "https://linktr.ee/nextgennorth",
                    "target": "_blank"
                }
            ]
        },
        "segment-3": {
            "title": "ENTREPRENEUR",
            "description": "JP Thor's entrepreneurial spirit is encapsulated in his diverse and dynamic ventures. Navigating the complexities of the crypto market to offering innovative helicopter hire solutions, JP Thor's projects reflect his commitment to pushing the envelope and creating impactful change.",
            "cards": [
                {
                    "title": "21e8 Capital",
                    "description": "A private Australian Crypto Fund trading on macro timelines.",
                    "url": "#",
                    "target": "_blank"
                },
                {
                    "title": "ARRQ",
                    "description": "Ad-hoc Helicopter Hire Solutions.",
                    "url": "#",
                    "target": "_blank"
                }
            ]
        },
        "segment-4": {
            "title": "EXPLORER",
            "description": "As an adventurous entrepreneur, JP Thor embarks on remarkable journeys and undertakes extraordinary projects. From pioneering expeditions to innovative ventures, explore the stories and insights that capture his relentless pursuit of excellence and exploration.",
            "cards": [
                {
                    "title": "Rotorhub: Australian entrepreneur signs for ACH125 and plans Poles expedition",
                    "url": "https://www.rotorhub.com/australian-entrepreneur-signs-for-ach125-and-plans-poles-expedition/",
                    "target": "_blank"
                },
                {
                    "title": "Aston Martin's ultra-luxe chopper arrives in Australia for the first time",
                    "url": "https://www.forbes.com.au/life/motors/aston-martins-ultra-luxe-chopper-arrives-in-australia-for-the-first-time/",
                    "target": "_blank"
                },
                {
                    "title": "Australian Entrepreneur plans Circumnavigation via Poles",
                    "url": "https://www.australianflying.com.au/helicopters/australian-entrepreneur-plans-circumnavigation-via-poles",
                    "target": "_blank"
                },
                {
                    "title": "The first-ever owner of the ACH130 Aston Martin Edition has the ultimate voyage in mind",
                    "url": "https://boulevard.co/post/jean-paul-thorbjornsen-aston-martin-helicopter/",
                    "target": "_blank"
                }
            ]
        }
    }
}